{
  "todos": [
    {
      "id": "XBC1Q9cageOhrlL6-fwRL",
      "text": "ottimo"
    },
    {
      "id": "VJRCP2KEjBEaXUXUHPzZc",
      "text": "ottimo"
    },
    {
      "id": "wzId5FU1PQK-EgmPIUiKB",
      "text": "che figata"
    },
    {
      "id": "VfuL06KzRtQAmKjphoMnx",
      "text": "veramente ottimo"
    },
    {
      "id": "ZnLXhkOtfu9-0CYDp3TWn",
      "text": "grazie a dio"
    },
    {
      "id": "RiX1qhRcYSmVf1wiiS164",
      "text": "adesso"
    },
    {
      "id": "tIX6WF3BtIoA6uW92T2TR",
      "text": "prova"
    },
    {
      "id": "lV_BRMfvVH785bJBdjBIN",
      "text": "aa"
    },
    {
      "id": "fhy3wBla8oQfTsgwBW6iD",
      "text": "aaa"
    }
  ]
}